MANIFEST.in
README.md
setup.py
zenda.py
zenda.egg-info/PKG-INFO
zenda.egg-info/SOURCES.txt
zenda.egg-info/dependency_links.txt
zenda.egg-info/top_level.txt